herethere/__init__.py
herethere/herethere_version.py
herethere/version.py
herethere/everywhere/__init__.py
herethere/everywhere/code.py
herethere/everywhere/config.py
herethere/everywhere/logging.py
herethere/everywhere/magic.py
herethere/everywhere/redirected_output.py
herethere/here/__init__.py
herethere/here/__main__.py
herethere/here/config.py
herethere/here/magic.py
herethere/here/server.py
herethere/magic/__init__.py
herethere/there/__init__.py
herethere/there/client.py
herethere/there/magic.py
herethere/there/output.py
herethere/there/commands/__init__.py
herethere/there/commands/core.py
herethere/there/commands/log.py
herethere-0.1.2.dist-info/LICENSE
herethere-0.1.2.dist-info/METADATA
herethere-0.1.2.dist-info/WHEEL
herethere-0.1.2.dist-info/top_level.txt
herethere-0.1.2.dist-info/RECORD
